FotMoby/FotMoby.py
FotMoby/__init__.py
fotmoby-0.0.5.dist-info/LICENSE
fotmoby-0.0.5.dist-info/METADATA
fotmoby-0.0.5.dist-info/WHEEL
fotmoby-0.0.5.dist-info/top_level.txt
fotmoby-0.0.5.dist-info/RECORD
